event_ticketmaster_graphql_imp_local/__init__.py
event_ticketmaster_graphql_imp_local/ticketmaster_event_constants.py
event_ticketmaster_graphql_imp_local/ticketmaster_local.py
event_ticketmaster_graphql_imp_local/util.py
event_ticketmaster_graphql_imp_local-0.0.6.dist-info/METADATA
event_ticketmaster_graphql_imp_local-0.0.6.dist-info/WHEEL
event_ticketmaster_graphql_imp_local-0.0.6.dist-info/top_level.txt
event_ticketmaster_graphql_imp_local-0.0.6.dist-info/RECORD
